lean_explore/__init__.py
lean_explore/config.py
lean_explore/api/__init__.py
lean_explore/api/client.py
lean_explore/cli/__init__.py
lean_explore/cli/data_commands.py
lean_explore/cli/display.py
lean_explore/cli/main.py
lean_explore/extract/__init__.py
lean_explore/extract/__main__.py
lean_explore/extract/doc_gen4.py
lean_explore/extract/doc_parser.py
lean_explore/extract/embeddings.py
lean_explore/extract/github.py
lean_explore/extract/index.py
lean_explore/extract/informalize.py
lean_explore/extract/package_config.py
lean_explore/extract/package_registry.py
lean_explore/extract/package_utils.py
lean_explore/extract/types.py
lean_explore/mcp/__init__.py
lean_explore/mcp/app.py
lean_explore/mcp/server.py
lean_explore/mcp/tools.py
lean_explore/models/__init__.py
lean_explore/models/search_db.py
lean_explore/models/search_types.py
lean_explore/search/__init__.py
lean_explore/search/engine.py
lean_explore/search/scoring.py
lean_explore/search/service.py
lean_explore/search/tokenization.py
lean_explore/util/__init__.py
lean_explore/util/embedding_client.py
lean_explore/util/logging.py
lean_explore/util/openrouter_client.py
lean_explore/util/reranker_client.py
lean_explore-1.2.0.dist-info/licenses/LICENSE
lean_explore-1.2.0.dist-info/METADATA
lean_explore-1.2.0.dist-info/WHEEL
lean_explore-1.2.0.dist-info/entry_points.txt
lean_explore-1.2.0.dist-info/top_level.txt
lean_explore-1.2.0.dist-info/RECORD
