Metadata-Version: 2.4
Name: lean-explore
Version: 1.2.0
Summary: A search engine for Lean 4 declarations.
Author-email: Justin Asher <justinchadwickasher@gmail.com>
License:                                  Apache License
Project-URL: Homepage, https://www.leanexplore.com/
Project-URL: Repository, https://github.com/justincasher/lean-explore
Keywords: lean,lean4,search,formal methods,theorem prover,math,AI
Classifier: Development Status :: 4 - Beta
Classifier: Intended Audience :: Developers
Classifier: Intended Audience :: Science/Research
Classifier: License :: OSI Approved :: Apache Software License
Classifier: Programming Language :: Python :: 3
Classifier: Programming Language :: Python :: 3.10
Classifier: Programming Language :: Python :: 3.11
Classifier: Programming Language :: Python :: 3.12
Classifier: Topic :: Software Development :: Libraries :: Python Modules
Classifier: Topic :: Scientific/Engineering :: Mathematics
Classifier: Topic :: Text Processing :: Indexing
Requires-Python: >=3.10
License-File: LICENSE
Requires-Dist: sqlalchemy>=2.0
Requires-Dist: aiosqlite>=0.19.0
Requires-Dist: greenlet>=3.0.0
Requires-Dist: numpy>=1.20
Requires-Dist: faiss-cpu>=1.7
Requires-Dist: filelock>=3.0.0
Requires-Dist: nltk>=3.6
Requires-Dist: bm25s>=0.2.0
Requires-Dist: httpx>=0.23.0
Requires-Dist: pydantic>=2.0
Requires-Dist: typer[all]>=0.9.0
Requires-Dist: toml>=0.10.0
Requires-Dist: openai-agents>=0.0.16
Requires-Dist: mcp>=1.9.0
Requires-Dist: tqdm>=4.60
Requires-Dist: rich>=13.0.0
Requires-Dist: requests>=2.25.0
Requires-Dist: tenacity>=8.0.0
Requires-Dist: pooch>=1.8.0
Provides-Extra: extract
Requires-Dist: sentence-transformers>=2.2.0; extra == "extract"
Requires-Dist: networkx>=3.0; extra == "extract"
Requires-Dist: torch>=2.0.0; extra == "extract"
Provides-Extra: dev
Requires-Dist: pytest>=7.0; extra == "dev"
Requires-Dist: pytest-cov>=4.0; extra == "dev"
Requires-Dist: pytest-asyncio>=0.21.0; extra == "dev"
Requires-Dist: ruff>=0.1.0; extra == "dev"
Requires-Dist: pre-commit>=3.0.0; extra == "dev"
Requires-Dist: networkx>=3.0; extra == "dev"
Requires-Dist: torch>=2.0.0; extra == "dev"
Requires-Dist: sentence-transformers>=2.2.0; extra == "dev"
Dynamic: license-file
